MANIFEST.in
README.md
setup.py
sentry_irccat/__init__.py
sentry_irccat/plugin.py
sentry_irccat.egg-info/PKG-INFO
sentry_irccat.egg-info/SOURCES.txt
sentry_irccat.egg-info/dependency_links.txt
sentry_irccat.egg-info/entry_points.txt
sentry_irccat.egg-info/not-zip-safe
sentry_irccat.egg-info/requires.txt
sentry_irccat.egg-info/top_level.txt