Metadata-Version: 1.0
Name: sentry-irccat
Version: 0.1.0
Summary: A Sentry extension which integrates with irccat
Home-page: http://www.github.com/russss
Author: Russ Garrett
Author-email: russ@garrett.co.uk
License: BSD
Platform: UNKNOWN
Classifier: Framework :: Django
Classifier: Intended Audience :: Developers
Classifier: Intended Audience :: System Administrators
Classifier: Operating System :: OS Independent
Classifier: Topic :: Software Development
